ink/__init__.py
ink/base/__init__.py
ink/base/connectors.py
ink/base/graph.py
ink/base/structure.py
ink/base/transform/__init__.py
ink/base/transform/binarize.py
ink/base/transform/counts.py
ink/base/transform/levels.py
ink/miner/__init__.py
ink/miner/rulemining.py
ink/miner/task_agnostic_mining.py
ink/miner/task_specific_mining.py
ink/miner/utils.py
semantic_ink-0.0.2.dist-info/LICENSE
semantic_ink-0.0.2.dist-info/METADATA
semantic_ink-0.0.2.dist-info/WHEEL
semantic_ink-0.0.2.dist-info/top_level.txt
semantic_ink-0.0.2.dist-info/RECORD
