Metadata-Version: 2.1
Name: semantic-ink
Version: 0.0.2
Summary: INK: Instance Neighbouring by using Knowledge
Home-page: https://github.com/IBCNServices/INK
Author: Bram Steenwinckel
Author-email: bram.steenwinckel@ugent.be
License: UNKNOWN
Project-URL: Source, https://github.com/IBCNServices/INK
Project-URL: Tracker, https://github.com/IBCNServices/INK/issues
Keywords: Knowledge graph representation,Semantic Rule Mining
Platform: UNKNOWN
Classifier: Programming Language :: Python :: 3.6
Classifier: Programming Language :: Python :: 3.7
Classifier: Programming Language :: Python :: 3.8
Classifier: Operating System :: OS Independent
